discord_autoupdate_secure/__init__.py
discord_autoupdate_secure/main.py
discord_autoupdate_secure-1.4.2.dist-info/licenses/LICENSE
discord_autoupdate_secure-1.4.2.dist-info/METADATA
discord_autoupdate_secure-1.4.2.dist-info/WHEEL
discord_autoupdate_secure-1.4.2.dist-info/entry_points.txt
discord_autoupdate_secure-1.4.2.dist-info/top_level.txt
discord_autoupdate_secure-1.4.2.dist-info/RECORD
