Metadata-Version: 2.4
Name: discord-autoupdate-secure
Version: 1.4.2
Summary: Makes your .deb Discord desktop icon update Discord securely.
Author-email: Chase Adams <chase.adams@gmail.com>
Project-URL: Homepage, https://github.com/curvedinf/discord-autoupdate-secure
Project-URL: Repository, https://github.com/curvedinf/discord-autoupdate-secure
Project-URL: Issues, https://github.com/curvedinf/discord-autoupdate-secure/issues
Classifier: Programming Language :: Python :: 3
Classifier: Programming Language :: Python :: 3 :: Only
Classifier: License :: OSI Approved :: MIT License
Classifier: Operating System :: POSIX :: Linux
Requires-Python: >=3.8
License-File: LICENSE
Requires-Dist: requests
Dynamic: license-file
